CHANGELOG.md
getmovieinfo/MovieInfo.py
getmovieinfo/WebCrawler/__init__.py
getmovieinfo/WebCrawler/firefox.py
getmovieinfo/WebCrawler/htmlclass.py
getmovieinfo/WebCrawler/myairav.py
getmovieinfo/WebCrawler/myavsox.py
getmovieinfo/WebCrawler/mycarib.py
getmovieinfo/WebCrawler/mydlsite.py
getmovieinfo/WebCrawler/myfanza.py
getmovieinfo/WebCrawler/myfc2.py
getmovieinfo/WebCrawler/myfc2club.py
getmovieinfo/WebCrawler/myjav321.py
getmovieinfo/WebCrawler/myjavbus.py
getmovieinfo/WebCrawler/myjavdb.py
getmovieinfo/WebCrawler/mymgstage.py
getmovieinfo/WebCrawler/mymv91.py
getmovieinfo/WebCrawler/register.py
getmovieinfo/WebCrawler/storyline.py
getmovieinfo-0.1.6.dist-info/entry_points.txt
getmovieinfo-0.1.6.dist-info/WHEEL
getmovieinfo-0.1.6.dist-info/METADATA
getmovieinfo-0.1.6.dist-info/RECORD
